Metadata-Version: 2.1
Name: gj-datac
Version: 0.1.0
Summary: gj_datac api
Home-page: UNKNOWN
Author: shuai yin
Author-email: 2018209921@qq.com
License: UNKNOWN
Platform: UNKNOWN
